{
  "scaler": 0.5,
  "rotationSpeed": [ "-30", "-20", "-10", "0", "0", "10", "20", "30"],
  "width": 5,
  "height": 5,
  "depth": 10,
  "backCircles": 40,
  "ceilCircles": 80,
  "wallCircles": 80,
  "buffer": [ "0.0" ],
  "control": [ "false", "true" ],
  "overlap": ["false", "true"],
  "spin": false,
  "x_range_min": 0.2,
  "x_range_max": 0.2,
  "y_range_min": 0.2,
  "y_range_max": 0.2,
  "z_range_min": 0.2,
  "z_range_max": 0.2,
  "trialTracker": 0,
  "conditionRepeat": 5,
  "staticStartTime": 1,
  "rotationTime": 3,
  "darknessEndTime": 2
}